notebooks/__init__.py
ollama/__init__.py
projects/__init__.py
projects/document_summarizer/__init__.py
projects/document_summarizer/summarizer.py
projects/langgraph_agents/__init__.py
projects/langgraph_agents/agents.py
projects/rag_with_faiss/__init__.py
projects/rag_with_faiss/rag.py
learn_genai-1.1.1.dist-info/METADATA
learn_genai-1.1.1.dist-info/WHEEL
learn_genai-1.1.1.dist-info/entry_points.txt
learn_genai-1.1.1.dist-info/top_level.txt
learn_genai-1.1.1.dist-info/RECORD
