Metadata-Version: 2.1
Name: learn_genai
Version: 1.1.1
Summary: Paquete para aprender Generative AI con ejemplos prácticos.
Home-page: https://github.com/fbanespo1/learn_genai
Author: Antonio Esposito
Author-email: fbanespo@gmail.com
Classifier: Programming Language :: Python :: 3
Classifier: License :: OSI Approved :: MIT License
Classifier: Operating System :: OS Independent
Requires-Python: >=3.8
Requires-Dist: numpy
Requires-Dist: pandas
Requires-Dist: streamlit
Requires-Dist: jupyter
Requires-Dist: PyPDF2
Requires-Dist: faiss-cpu
Requires-Dist: langchain
Requires-Dist: langgraph
Requires-Dist: transformers
Requires-Dist: torch
